bayesiannetworkai/__init__.py
bayesiannetworkai/bayesiannetworkai.py
bayesiannetworkai/main.py
bayesiannetworkai-0.2.2.dist-info/METADATA
bayesiannetworkai-0.2.2.dist-info/WHEEL
bayesiannetworkai-0.2.2.dist-info/LICENSE
bayesiannetworkai-0.2.2.dist-info/RECORD
