Metadata-Version: 2.1
Name: bayesiannetworkai
Version: 0.2.2
Summary: A package for using Bayesian Networks
License: MIT
Author: GrupoAI
Requires-Python: >=3.8,<4.0
Classifier: License :: OSI Approved :: MIT License
Classifier: Programming Language :: Python :: 3
Classifier: Programming Language :: Python :: 3.8
Classifier: Programming Language :: Python :: 3.9
Classifier: Programming Language :: Python :: 3.10
Classifier: Programming Language :: Python :: 3.11
Requires-Dist: pgmpy (>=0.1.21,<0.2.0)
